{"assets/images/default_female.png":["assets/images/default_female.png"],"assets/images/default_female2.png":["assets/images/default_female2.png"],"assets/images/default_male.png":["assets/images/default_male.png"],"assets/images/default_nonbinary.png":["assets/images/default_nonbinary.png"],"assets/images/logo.svg":["assets/images/logo.svg"],"assets/images/profile_placeholder.svg":["assets/images/profile_placeholder.svg"],"assets/images/ranks/astra.svg":["assets/images/ranks/astra.svg"],"assets/images/ranks/bronze.svg":["assets/images/ranks/bronze.svg"],"assets/images/ranks/celestial.svg":["assets/images/ranks/celestial.svg"],"assets/images/ranks/diamond.svg":["assets/images/ranks/diamond.svg"],"assets/images/ranks/gold.svg":["assets/images/ranks/gold.svg"],"assets/images/ranks/grandmaster.svg":["assets/images/ranks/grandmaster.svg"],"assets/images/ranks/iron.svg":["assets/images/ranks/iron.svg"],"assets/images/ranks/jade.svg":["assets/images/ranks/jade.svg"],"assets/images/ranks/master.svg":["assets/images/ranks/master.svg"],"assets/images/ranks/nova.svg":["assets/images/ranks/nova.svg"],"assets/images/ranks/platinum.svg":["assets/images/ranks/platinum.svg"],"assets/images/ranks/silver.svg":["assets/images/ranks/silver.svg"],"assets/images/ranks/unranked.svg":["assets/images/ranks/unranked.svg"],"assets/images/rare_female.png":["assets/images/rare_female.png"],"assets/images/routine_placeholder.png":["assets/images/routine_placeholder.png"],"assets/images/routine_placeholder.svg":["assets/images/routine_placeholder.svg"],"packages/cupertino_icons/assets/CupertinoIcons.ttf":["packages/cupertino_icons/assets/CupertinoIcons.ttf"]}